compile/regfile32.v
module regfile32 (read1, read2, writeto, writedat, writeenable, out1, out2, clock, reset);
//Performance Cost: 5 + 1
input [4:0] read1; //Register to check
input [4:0] read2; //Register to check
input [4:0] writeto; //register # to write to
input [31:0] writedat; //data to be written to writeto register
input writeenable, clock, reset;
wire [31:0] Y0, Y1, Y2;
output reg [31:0] out1, out2;
// 32 bit registers x 32, do not use register 0
reg [31:0] RF [31:0];

integer signextendbit = 0;
//Makes read1 and read2 compatible with our RF 32 bit register, sign extending this
//in the process
assign Y0 = {{27{signextendbit}}, read1};
assign Y1 = {{27{signextendbit}}, read2};
//assign Y2 = {{27{signextendbit}}, writeto};

integer i;
always @ (posedge clock, posedge reset)
begin

	if (reset == 1)
	begin
		for (i = 0; i <= 31; i = i + 1)
		begin
			//zero out RF
			RF[i] = 32'd0;
		end
	end
		if (writeenable == 1)
		begin
			//#420 Trial 1
			//assign writeto = {{28{writeto[4]}}, writeto};
			//#471 //#530 - 29
			RF[writeto] <= writedat;
			$display("RF[writeto] <= writedat is here!!!");
		end

		//#400 //Don't change unless it bleeds into another cycle
		//$display("Register[writeto] %b", RF[writeto]);
		//$display("Register File out1: %b", out1);
		//$display("Register File out2: %b", out2);
		for (i = 0; i < 32; i = i + 1) begin
		$display("register%d: %b", i, RF[i]);
		end

		out1 <= RF[Y0];
		out2 <= RF[Y1];
		$display("out1: %b", out1);
		$display("out2: %b", out2);
	end
		//Under the always block

endmodule //regfile32

compile/regfile32test.v
module regfile32test ();
//Performance Cost: 5 + 1
reg [4:0] read1;
reg [4:0] read2;
reg [4:0] writeto; //register # to write to
reg [31:0] writedat; //data to be written to writeto register
reg writeenable, clock, reset;
wire [31:0] out1, out2;
// 32 bit registers x 32, do not use register 0
reg [31:0] RF [31:0];

regfile32 DUT(read1, read2, writeto, writedat, writeenable, out1, out2, clock, reset);
initial begin
    $dumpfile("gtk/regfile32-gtkwave.vcd");
    $dumpvars(0, DUT);

    $display("\nInitialize Values with reset");
    //Initialize our Registers with our 0's
    reset <= 0;
    #6
    reset <= 1;
    #6
    reset <= 0;
    #6
    //$display("RegOut1: %b", out1);
    //$display("RegOut2: %b", out2);

    //Tests for writeenable being off, meaning nothing should occur
    $display("\nFirst Test with write enable 0");
    clock <= 0;
    writeenable <= 0;
    read1 <= 5'd0;
    read2 <= 5'd0;
    writeto <= 5'd1;
    writedat <= 32'd200;
    clock <= 1;
    #6
    $display("read1: %b", read1);
    $display("read2: %b", read2);
    $display("writeto (regAddress): %b", writeto);
    $display("writedat: %b", writedat);
    $display("Output====");
    //$display("RegOut1: %b", out1);
    //$display("RegOut2: %b", out2);

    $display("\nWrite Enable--> 200 to regAddr1");
    clock <= 0;
    writeenable <= 1;
    read1 <= 5'd0;
    read2 <= 5'd0;
    writeto <= 5'd1;
    writedat <= 32'd200;
    clock <= 1;
    #6
    $display("read1: %b", read1);
    $display("read2: %b", read2);
    $display("writeto (regAddress): %b", writeto);
    $display("writedat: %b", writedat);
    $display("Outputs=========");
    //$display("RegOut1: %b", out1);
    //$display("RegOut2: %b", out2);
    //The problem with this is that we don't have permission to write to the register
    //So we have to test this within our regfile32
    //$display("Register File Out %b\n", RF[writeto]);

    $display("\nWrite Enable--> 300 to regAddr2");
    clock <= 0;
    #6
    clock <= 1;
    writeenable <= 1;
    read1 <= 5'd5;
    read2 <= 5'd6;
    writeto <= 5'd2;
    writedat <= 32'd300; //W1 should be 2 in binary, works
    clock <= 1;
    #6
    $display("read1: %b", read1);
    $display("read2: %b", read2);
    $display("writeto (regAddress): %b", writeto);
    $display("writedat: %b", writedat);
    $display("Outputs=========");
    //$display("RegOut1: %b", out1);
    //$display("RegOut2: %b", out2);


    $display("\nRead from our previously written registers");
    clock <= 0;
    #6
    clock <= 1;
    writeenable <= 1;
    read1 <= 5'd1;
    read2 <= 5'd2;
    writeto <= 5'd3;
    writedat <= 32'd3; //should be 3 in binary, is
    clock <= 1;
    #6
    $display("read1: %b", read1);
    $display("read2: %b", read2);
    $display("writeto (regAddress): %b", writeto);
    $display("writedat: %b", writedat);
    $display("Outputs=========");
    //$display("RegOut1: %b", out1);
    //$display("RegOut2: %b", out2);
end
endmodule // regfile32test

compile/mux21.v
module mux21 (inA, inB, inS, outO);
//Performance Cost: #9

input wire inA, //data wire A
	inB, //data wire B
	inS; //selector wire
wire Snot; //transition from not to in1 input
wire T1, T2; //transition wires from nand to or gate
output wire outO;
	//O = A if S = 0
	//O = B if S = 1
not #1 (Snot, inS);
and #4 (T1, inA, Snot); //inA nand
and #4 (T2, inB, inS); //inB nand
or #4 (outO, T1, T2); //outO or

endmodule //mux21

compile/mux51.v
module mux51 (inA, inB, inS, outO);

//an array of 5 wires to use for each of the muxes
input wire [4:0] inA;
input wire [4:0] inB;
input wire inS;
output wire [4:0] outO;
mux21 mux0(inA[0], inB[0], inS, outO[0]);
mux21 mux1(inA[1], inB[1], inS, outO[1]);
mux21 mux2(inA[2], inB[2], inS, outO[2]);
mux21 mux3(inA[3], inB[3], inS, outO[3]);
mux21 mux4(inA[4], inB[4], inS, outO[4]);

endmodule //mux51

compile/mux51test.v
module mux51test();
//Performance Cost: 9 + 1?
reg [4:0] inA, inB;
reg inS;
wire [4:0] outO;

mux51 DUT(inA, inB, inS, outO);
initial
begin
	$dumpfile("gtk/mux51-gtkwave.vcd");
	$dumpvars(0, DUT);

	$display("Test Start");
	inA <= 5'b01110;
	inB <= 5'b10001;
	inS <= 0;
	#10
	$display("inA = %b\ninB = %b\ninS = %b", inA, inB, inS);
	$display("outO is = %b\n", outO);

	inA <= 5'b01110;
	inB <= 5'b10001;
	inS <= 1;
	#10
	$display("inA = %b\ninB = %b\ninS = %b", inA, inB, inS);
	$display("outO is = %b\n", outO);

	inA <= 5'b10001;
	inB <= 5'b01110;
	inS <= 0;
	#10
	$display("inA = %b\ninB = %b\ninS = %b", inA, inB, inS);
	$display("outO is = %b\n", outO);

	inA <= 5'b10001;
	inB <= 5'b01110;
	inS <= 1;
	#10
	$display("inA = %b\ninB = %b\ninS = %b", inA, inB, inS);
	$display("outO is = %b\n", outO);
end
endmodule

compile/mux32.v
module mux32 (inA, inB, inS, outO);
    input wire [31:0] inA;
    input wire [31:0] inB;
    input wire inS;
    output wire [31:0] outO;

    initial begin
    //#460
    //$display("Output of Mux: %b", outO);
    end

    mux21 mux0(inA[0], inB[0], inS, outO[0]);
    mux21 mux1(inA[1], inB[1], inS, outO[1]);
    mux21 mux2(inA[2], inB[2], inS, outO[2]);
    mux21 mux3(inA[3], inB[3], inS, outO[3]);
    mux21 mux4(inA[4], inB[4], inS, outO[4]);
    mux21 mux5(inA[5], inB[5], inS, outO[5]);
    mux21 mux6(inA[6], inB[6], inS, outO[6]);
    mux21 mux7(inA[7], inB[7], inS, outO[7]);
    mux21 mux8(inA[8], inB[8], inS, outO[8]);
    mux21 mux9(inA[9], inB[9], inS, outO[9]);
    mux21 mux10(inA[10], inB[10], inS, outO[10]);
    mux21 mux11(inA[11], inB[11], inS, outO[11]);
    mux21 mux12(inA[12], inB[12], inS, outO[12]);
    mux21 mux13(inA[13], inB[13], inS, outO[13]);
    mux21 mux14(inA[14], inB[14], inS, outO[14]);
    mux21 mux15(inA[15], inB[15], inS, outO[15]);
    mux21 mux16(inA[16], inB[16], inS, outO[16]);
    mux21 mux17(inA[17], inB[17], inS, outO[17]);
    mux21 mux18(inA[18], inB[18], inS, outO[18]);
    mux21 mux19(inA[19], inB[19], inS, outO[19]);
    mux21 mux20(inA[20], inB[20], inS, outO[20]);
    mux21 mux21(inA[21], inB[21], inS, outO[21]);
    mux21 mux22(inA[22], inB[22], inS, outO[22]);
    mux21 mux23(inA[23], inB[23], inS, outO[23]);
    mux21 mux24(inA[24], inB[24], inS, outO[24]);
    mux21 mux25(inA[25], inB[25], inS, outO[25]);
    mux21 mux26(inA[26], inB[26], inS, outO[26]);
    mux21 mux27(inA[27], inB[27], inS, outO[27]);
    mux21 mux28(inA[28], inB[28], inS, outO[28]);
    mux21 mux29(inA[29], inB[29], inS, outO[29]);
    mux21 mux30(inA[30], inB[30], inS, outO[30]);
    mux21 mux31(inA[31], inB[31], inS, outO[31]);

endmodule //mux32

compile/mux32test.v
module mux32test();
//Performance Cost: #9 + 1
reg [31:0] inA, inB;
reg inS;
wire [31:0] outO;

mux32 DUT(inA, inB, inS, outO);
initial
begin
	$dumpfile("gtk/mux32-gtkwave.vcd");
	$dumpvars(0, DUT);

	$display("Test Start");
	//there's a better way to do this.
	inA <= 32'b00000000000000000000000000000001;
	inB <= 32'b10000000000000000000000000000000;
	inS <= 0;
	#10
	$display("inA: %b\ninB: %b\ninS: %b", inA, inB, inS);
	$display("outO is = %b\n", outO);

	inA <= 32'b00000000000000000000000000000001;
	inB <= 32'b10000000000000000000000000000000;
	inS <= 1;
	#10
	$display("inA: %b\ninB: %b\ninS: %b", inA, inB, inS);
	$display("outO is = %b\n", outO);

	inA <= 32'b10000000000000000000000000000000;
	inB <= 32'b00000000000000000000000000000001;
	inS <= 0;
	#10
	$display("inA: %b\ninB: %b\ninS: %b", inA, inB, inS);
	$display("outO is = %b\n", outO);

	inA <= 32'b10000000000000000000000000000000;
	inB <= 32'b00000000000000000000000000000001;
	inS <= 1;
	#10
	$display("inA: %b\ninB: %b\ninS: %b", inA, inB, inS);
	$display("outO is = %b\n", outO);
end
endmodule

compile/mux21test.v
module mux21test();
//Performance Cost: #9 for single bit, so why 14 down in the test?
reg inA, inB, inS;
wire outO;

mux21 DUT(inA, inB, inS, outO);
initial
begin
	$dumpfile("gtk/mux21-gtkwave.vcd");
	$dumpvars(0, DUT);

    //with inS = 0, inA will be chosen
	$display("Test Start");
	inA <= 0;
	inB <= 0;
	inS <= 0;
	#14
	$display("A/B/S is 0/0/0");
	$display("outO = %d\n", outO);

	inA <= 1;
	inB <= 0;
	inS <= 0;
	#14
	$display("A/B/S is 1/0/0");
	$display("outO = %d\n", outO);

	inA <= 0;
	inB <= 1;
	inS <= 0;
	#14
	$display("A/B/S is 0/1/0");
	$display("outO = %d\n", outO);

	inA <= 1;
	inB <= 1;
	inS <= 0;
	#14
	$display("A/B/S is 1/1/0");
	$display("outO = %d\n", outO);

	inA <= 0;
	inB <= 0;
	inS <= 1;
	#14
	$display("A/B/S is 0/0/1");
	$display("outO = %d\n", outO);

	inA <= 0;
	inB <= 1;
	inS <= 1;
	#14
	$display("A/B/S is 0/1/1");
	$display("outO = %d\n", outO);

	inA <= 1;
	inB <= 0;
	inS <= 1;
	#14
	$display("A/B/S is 1/0/1");
	$display("outO = %d\n", outO);

	inA <= 1;
	inB <= 1;
	inS <= 1;
	#14
	$display("A/B/S is 1/1/1");
	$display("outO = %d\n", outO);
end
endmodule

gtk/mux21-gtkwave.vcd
$date
	Thu Apr  4 19:32:10 2019
$end
$version
	Icarus Verilog
$end
$timescale
	1s
$end
$scope module mux21test $end
$scope module DUT $end
$var wire 1 ! Snot $end
$var wire 1 " T1 $end
$var wire 1 # T2 $end
$var wire 1 $ inA $end
$var wire 1 % inB $end
$var wire 1 & inS $end
$var wire 1 ' outO $end
$upscope $end
$upscope $end
$scope module mux32test $end
$scope module DUT $end
$var wire 32 ( inA [31:0] $end
$var wire 32 ) inB [31:0] $end
$var wire 1 * inS $end
$var wire 32 + outO [31:0] $end
$scope module mux0 $end
$var wire 1 , Snot $end
$var wire 1 - T1 $end
$var wire 1 . T2 $end
$var wire 1 / inA $end
$var wire 1 0 inB $end
$var wire 1 * inS $end
$var wire 1 1 outO $end
$upscope $end
$scope module mux1 $end
$var wire 1 2 Snot $end
$var wire 1 3 T1 $end
$var wire 1 4 T2 $end
$var wire 1 5 inA $end
$var wire 1 6 inB $end
$var wire 1 * inS $end
$var wire 1 7 outO $end
$upscope $end
$scope module mux10 $end
$var wire 1 8 Snot $end
$var wire 1 9 T1 $end
$var wire 1 : T2 $end
$var wire 1 ; inA $end
$var wire 1 < inB $end
$var wire 1 * inS $end
$var wire 1 = outO $end
$upscope $end
$scope module mux11 $end
$var wire 1 > Snot $end
$var wire 1 ? T1 $end
$var wire 1 @ T2 $end
$var wire 1 A inA $end
$var wire 1 B inB $end
$var wire 1 * inS $end
$var wire 1 C outO $end
$upscope $end
$scope module mux12 $end
$var wire 1 D Snot $end
$var wire 1 E T1 $end
$var wire 1 F T2 $end
$var wire 1 G inA $end
$var wire 1 H inB $end
$var wire 1 * inS $end
$var wire 1 I outO $end
$upscope $end
$scope module mux13 $end
$var wire 1 J Snot $end
$var wire 1 K T1 $end
$var wire 1 L T2 $end
$var wire 1 M inA $end
$var wire 1 N inB $end
$var wire 1 * inS $end
$var wire 1 O outO $end
$upscope $end
$scope module mux14 $end
$var wire 1 P Snot $end
$var wire 1 Q T1 $end
$var wire 1 R T2 $end
$var wire 1 S inA $end
$var wire 1 T inB $end
$var wire 1 * inS $end
$var wire 1 U outO $end
$upscope $end
$scope module mux15 $end
$var wire 1 V Snot $end
$var wire 1 W T1 $end
$var wire 1 X T2 $end
$var wire 1 Y inA $end
$var wire 1 Z inB $end
$var wire 1 * inS $end
$var wire 1 [ outO $end
$upscope $end
$scope module mux16 $end
$var wire 1 \ Snot $end
$var wire 1 ] T1 $end
$var wire 1 ^ T2 $end
$var wire 1 _ inA $end
$var wire 1 ` inB $end
$var wire 1 * inS $end
$var wire 1 a outO $end
$upscope $end
$scope module mux17 $end
$var wire 1 b Snot $end
$var wire 1 c T1 $end
$var wire 1 d T2 $end
$var wire 1 e inA $end
$var wire 1 f inB $end
$var wire 1 * inS $end
$var wire 1 g outO $end
$upscope $end
$scope module mux18 $end
$var wire 1 h Snot $end
$var wire 1 i T1 $end
$var wire 1 j T2 $end
$var wire 1 k inA $end
$var wire 1 l inB $end
$var wire 1 * inS $end
$var wire 1 m outO $end
$upscope $end
$scope module mux19 $end
$var wire 1 n Snot $end
$var wire 1 o T1 $end
$var wire 1 p T2 $end
$var wire 1 q inA $end
$var wire 1 r inB $end
$var wire 1 * inS $end
$var wire 1 s outO $end
$upscope $end
$scope module mux2 $end
$var wire 1 t Snot $end
$var wire 1 u T1 $end
$var wire 1 v T2 $end
$var wire 1 w inA $end
$var wire 1 x inB $end
$var wire 1 * inS $end
$var wire 1 y outO $end
$upscope $end
$scope module mux20 $end
$var wire 1 z Snot $end
$var wire 1 { T1 $end
$var wire 1 | T2 $end
$var wire 1 } inA $end
$var wire 1 ~ inB $end
$var wire 1 * inS $end
$var wire 1 !" outO $end
$upscope $end
$scope module mux21 $end
$var wire 1 "" Snot $end
$var wire 1 #" T1 $end
$var wire 1 $" T2 $end
$var wire 1 %" inA $end
$var wire 1 &" inB $end
$var wire 1 * inS $end
$var wire 1 '" outO $end
$upscope $end
$scope module mux22 $end
$var wire 1 (" Snot $end
$var wire 1 )" T1 $end
$var wire 1 *" T2 $end
$var wire 1 +" inA $end
$var wire 1 ," inB $end
$var wire 1 * inS $end
$var wire 1 -" outO $end
$upscope $end
$scope module mux23 $end
$var wire 1 ." Snot $end
$var wire 1 /" T1 $end
$var wire 1 0" T2 $end
$var wire 1 1" inA $end
$var wire 1 2" inB $end
$var wire 1 * inS $end
$var wire 1 3" outO $end
$upscope $end
$scope module mux24 $end
$var wire 1 4" Snot $end
$var wire 1 5" T1 $end
$var wire 1 6" T2 $end
$var wire 1 7" inA $end
$var wire 1 8" inB $end
$var wire 1 * inS $end
$var wire 1 9" outO $end
$upscope $end
$scope module mux25 $end
$var wire 1 :" Snot $end
$var wire 1 ;" T1 $end
$var wire 1 <" T2 $end
$var wire 1 =" inA $end
$var wire 1 >" inB $end
$var wire 1 * inS $end
$var wire 1 ?" outO $end
$upscope $end
$scope module mux26 $end
$var wire 1 @" Snot $end
$var wire 1 A" T1 $end
$var wire 1 B" T2 $end
$var wire 1 C" inA $end
$var wire 1 D" inB $end
$var wire 1 * inS $end
$var wire 1 E" outO $end
$upscope $end
$scope module mux27 $end
$var wire 1 F" Snot $end
$var wire 1 G" T1 $end
$var wire 1 H" T2 $end
$var wire 1 I" inA $end
$var wire 1 J" inB $end
$var wire 1 * inS $end
$var wire 1 K" outO $end
$upscope $end
$scope module mux28 $end
$var wire 1 L" Snot $end
$var wire 1 M" T1 $end
$var wire 1 N" T2 $end
$var wire 1 O" inA $end
$var wire 1 P" inB $end
$var wire 1 * inS $end
$var wire 1 Q" outO $end
$upscope $end
$scope module mux29 $end
$var wire 1 R" Snot $end
$var wire 1 S" T1 $end
$var wire 1 T" T2 $end
$var wire 1 U" inA $end
$var wire 1 V" inB $end
$var wire 1 * inS $end
$var wire 1 W" outO $end
$upscope $end
$scope module mux3 $end
$var wire 1 X" Snot $end
$var wire 1 Y" T1 $end
$var wire 1 Z" T2 $end
$var wire 1 [" inA $end
$var wire 1 \" inB $end
$var wire 1 * inS $end
$var wire 1 ]" outO $end
$upscope $end
$scope module mux30 $end
$var wire 1 ^" Snot $end
$var wire 1 _" T1 $end
$var wire 1 `" T2 $end
$var wire 1 a" inA $end
$var wire 1 b" inB $end
$var wire 1 * inS $end
$var wire 1 c" outO $end
$upscope $end
$scope module mux31 $end
$var wire 1 d" Snot $end
$var wire 1 e" T1 $end
$var wire 1 f" T2 $end
$var wire 1 g" inA $end
$var wire 1 h" inB $end
$var wire 1 * inS $end
$var wire 1 i" outO $end
$upscope $end
$scope module mux4 $end
$var wire 1 j" Snot $end
$var wire 1 k" T1 $end
$var wire 1 l" T2 $end
$var wire 1 m" inA $end
$var wire 1 n" inB $end
$var wire 1 * inS $end
$var wire 1 o" outO $end
$upscope $end
$scope module mux5 $end
$var wire 1 p" Snot $end
$var wire 1 q" T1 $end
$var wire 1 r" T2 $end
$var wire 1 s" inA $end
$var wire 1 t" inB $end
$var wire 1 * inS $end
$var wire 1 u" outO $end
$upscope $end
$scope module mux6 $end
$var wire 1 v" Snot $end
$var wire 1 w" T1 $end
$var wire 1 x" T2 $end
$var wire 1 y" inA $end
$var wire 1 z" inB $end
$var wire 1 * inS $end
$var wire 1 {" outO $end
$upscope $end
$scope module mux7 $end
$var wire 1 |" Snot $end
$var wire 1 }" T1 $end
$var wire 1 ~" T2 $end
$var wire 1 !# inA $end
$var wire 1 "# inB $end
$var wire 1 * inS $end
$var wire 1 ## outO $end
$upscope $end
$scope module mux8 $end
$var wire 1 $# Snot $end
$var wire 1 %# T1 $end
$var wire 1 &# T2 $end
$var wire 1 '# inA $end
$var wire 1 (# inB $end
$var wire 1 * inS $end
$var wire 1 )# outO $end
$upscope $end
$scope module mux9 $end
$var wire 1 *# Snot $end
$var wire 1 +# T1 $end
$var wire 1 ,# T2 $end
$var wire 1 -# inA $end
$var wire 1 .# inB $end
$var wire 1 * inS $end
$var wire 1 /# outO $end
$upscope $end
$upscope $end
$upscope $end
$scope module mux51test $end
$scope module DUT $end
$var wire 5 0# inA [4:0] $end
$var wire 5 1# inB [4:0] $end
$var wire 1 2# inS $end
$var wire 5 3# outO [4:0] $end
$scope module mux0 $end
$var wire 1 4# Snot $end
$var wire 1 5# T1 $end
$var wire 1 6# T2 $end
$var wire 1 7# inA $end
$var wire 1 8# inB $end
$var wire 1 2# inS $end
$var wire 1 9# outO $end
$upscope $end
$scope module mux1 $end
$var wire 1 :# Snot $end
$var wire 1 ;# T1 $end
$var wire 1 <# T2 $end
$var wire 1 =# inA $end
$var wire 1 ># inB $end
$var wire 1 2# inS $end
$var wire 1 ?# outO $end
$upscope $end
$scope module mux2 $end
$var wire 1 @# Snot $end
$var wire 1 A# T1 $end
$var wire 1 B# T2 $end
$var wire 1 C# inA $end
$var wire 1 D# inB $end
$var wire 1 2# inS $end
$var wire 1 E# outO $end
$upscope $end
$scope module mux3 $end
$var wire 1 F# Snot $end
$var wire 1 G# T1 $end
$var wire 1 H# T2 $end
$var wire 1 I# inA $end
$var wire 1 J# inB $end
$var wire 1 2# inS $end
$var wire 1 K# outO $end
$upscope $end
$scope module mux4 $end
$var wire 1 L# Snot $end
$var wire 1 M# T1 $end
$var wire 1 N# T2 $end
$var wire 1 O# inA $end
$var wire 1 P# inB $end
$var wire 1 2# inS $end
$var wire 1 Q# outO $end
$upscope $end
$upscope $end
$upscope $end
$scope module regfile32test $end
$scope module DUT $end
$var wire 1 R# clock $end
$var wire 5 S# read1 [4:0] $end
$var wire 5 T# read2 [4:0] $end
$var wire 1 U# reset $end
$var wire 32 V# writedat [31:0] $end
$var wire 1 W# writeenable $end
$var wire 5 X# writeto [4:0] $end
$var wire 32 Y# Y1 [31:0] $end
$var wire 32 Z# Y0 [31:0] $end
$var reg 32 [# out1 [31:0] $end
$var reg 32 \# out2 [31:0] $end
$var integer 32 ]# i [31:0] $end
$var integer 32 ^# signextendbit [31:0] $end
$upscope $end
$upscope $end
$enddefinitions $end
#0
$dumpvars
b0 ^#
bx ]#
bx \#
bx [#
b0xxxxx Z#
b0xxxxx Y#
bx X#
xW#
bx V#
0U#
bx T#
bx S#
xR#
xQ#
1P#
0O#
xN#
xM#
xL#
xK#
0J#
1I#
xH#
xG#
xF#
xE#
0D#
1C#
xB#
xA#
x@#
x?#
0>#
1=#
x<#
x;#
x:#
x9#
18#
07#
x6#
x5#
x4#
bx 3#
02#
b10001 1#
b1110 0#
x/#
0.#
0-#
x,#
x+#
x*#
x)#
0(#
0'#
x&#
x%#
x$#
x##
0"#
0!#
x~"
x}"
x|"
x{"
0z"
0y"
xx"
xw"
xv"
xu"
0t"
0s"
xr"
xq"
xp"
xo"
0n"
0m"
xl"
xk"
xj"
xi"
1h"
0g"
xf"
xe"
xd"
xc"
0b"
0a"
x`"
x_"
x^"
x]"
0\"
0["
xZ"
xY"
xX"
xW"
0V"
0U"
xT"
xS"
xR"
xQ"
0P"
0O"
xN"
xM"
xL"
xK"
0J"
0I"
xH"
xG"
xF"
xE"
0D"
0C"
xB"
xA"
x@"
x?"
0>"
0="
x<"
x;"
x:"
x9"
08"
07"
x6"
x5"
x4"
x3"
02"
01"
x0"
x/"
x."
x-"
0,"
0+"
x*"
x)"
x("
x'"
0&"
0%"
x$"
x#"
x""
x!"
0~
0}
x|
x{
xz
xy
0x
0w
xv
xu
xt
xs
0r
0q
xp
xo
xn
xm
0l
0k
xj
xi
xh
xg
0f
0e
xd
xc
xb
xa
0`
0_
x^
x]
x\
x[
0Z
0Y
xX
xW
xV
xU
0T
0S
xR
xQ
xP
xO
0N
0M
xL
xK
xJ
xI
0H
0G
xF
xE
xD
xC
0B
0A
x@
x?
x>
x=
0<
0;
x:
x9
x8
x7
06
05
x4
x3
x2
x1
00
1/
x.
x-
x,
bx +
0*
b10000000000000000000000000000000 )
b1 (
x'
0&
0%
0$
x#
x"
x!
$end
#1
14#
1:#
1@#
1F#
1L#
1,
12
18
1>
1D
1J
1P
1V
1\
1b
1h
1n
1t
1z
1""
1("
1."
14"
1:"
1@"
1F"
1L"
1R"
1X"
1^"
1d"
1j"
1p"
1v"
1|"
1$#
1*#
1!
#4
05#
0M#
03
0u
0Y"
0k"
0q"
0w"
0}"
0%#
0+#
09
0?
0E
0K
0Q
0W
0]
0c
0i
0o
0{
0#"
0)"
0/"
05"
0;"
0A"
0G"
0M"
0S"
0_"
0e"
06#
0<#
0B#
0H#
0N#
0.
04
0:
0@
0F
0L
0R
0X
0^
0d
0j
0p
0v
0|
0$"
0*"
00"
06"
0<"
0B"
0H"
0N"
0T"
0Z"
0`"
0f"
0l"
0r"
0x"
0~"
0&#
0,#
0#
0"
#5
1;#
1A#
1G#
1-
#6
b100000 ]#
1U#
#8
09#
b0xxx0 3#
0Q#
07
0=
0C
0I
0O
0U
0[
0a
0g
0m
0s
0y
0!"
0'"
0-"
03"
09"
0?"
0E"
0K"
0Q"
0W"
0]"
0c"
0i"
0o"
0u"
0{"
0##
0)#
b0x +
0/#
0'
#9
1?#
1E#
b1110 3#
1K#
b1 +
11
#10
12#
1*
#11
04#
0:#
0@#
0F#
0L#
0,
02
08
0>
0D
0J
0P
0V
0\
0b
0h
0n
0t
0z
0""
0("
0."
04"
0:"
0@"
0F"
0L"
0R"
0X"
0^"
0d"
0j"
0p"
0v"
0|"
0$#
0*#
#12
0U#
#14
1$
16#
1N#
1f"
#15
0;#
0A#
0G#
0-
#18
b0 \#
b0 [#
b0 Y#
b0 Z#
b11001000 V#
b1 X#
b0 T#
b0 S#
0W#
1R#
1"
19#
b11111 3#
1Q#
b10000000000000000000000000000001 +
1i"
#19
0?#
0E#
b10001 3#
0K#
b10000000000000000000000000000000 +
01
#20
08#
1>#
1D#
1J#
0P#
17#
0=#
0C#
0I#
1O#
10
0h"
0/
1g"
02#
b1110 1#
b10001 0#
0*
b1 )
b10000000000000000000000000000000 (
#21
14#
1:#
1@#
1F#
1L#
1,
12
18
1>
1D
1J
1P
1V
1\
1b
1h
1n
1t
1z
1""
1("
1."
14"
1:"
1@"
1F"
1L"
1R"
1X"
1^"
1d"
1j"
1p"
1v"
1|"
1$#
1*#
#22
1'
#24
1W#
1R#
06#
0N#
0f"
#25
15#
1M#
1e"
#28
1%
0$
#30
0R#
12#
1*
#31
04#
0:#
0@#
0F#
0L#
0,
02
08
0>
0D
0J
0P
0V
0\
0b
0h
0n
0t
0z
0""
0("
0."
04"
0:"
0@"
0F"
0L"
0R"
0X"
0^"
0d"
0j"
0p"
0v"
0|"
0$#
0*#
#32
0"
#34
1<#
1B#
1H#
1.
#35
05#
0M#
0e"
#36
b100101100 V#
b10 X#
1R#
0'
#38
1?#
1E#
b11111 3#
1K#
b10000000000000000000000000000001 +
11
#39
09#
b1110 3#
0Q#
b1 +
0i"
#42
0R#
1$
#46
1"
#48
b10 Y#
b1 Z#
b11 V#
b11 X#
b10 T#
b1 S#
1R#
#49
b100101100 \#
b11001000 [#
#50
1'
#56
1&
0%
0$
#57
0!
#60
0"
#64
0'
