compile/mux21.v
module mux21 (inA, inB, inS, outO);
//Performance Cost: #9

input wire inA, //data wire A
	inB, //data wire B
	inS; //selector wire
wire Snot; //transition from not to in1 input
wire T1, T2; //transition wires from nand to or gate
output wire outO;
	//O = A if S = 0
	//O = B if S = 1
not #1 (Snot, inS);
and #4 (T1, inA, Snot); //inA nand
and #4 (T2, inB, inS); //inB nand
or #4 (outO, T1, T2); //outO or

endmodule //mux21

compile/mux51.v
module mux51 (inA, inB, inS, outO);

//an array of 5 wires to use for each of the muxes
input wire [4:0] inA;
input wire [4:0] inB;
input wire inS;
output wire [4:0] outO;
mux21 mux0(inA[0], inB[0], inS, outO[0]);
mux21 mux1(inA[1], inB[1], inS, outO[1]);
mux21 mux2(inA[2], inB[2], inS, outO[2]);
mux21 mux3(inA[3], inB[3], inS, outO[3]);
mux21 mux4(inA[4], inB[4], inS, outO[4]);

endmodule //mux51

compile/mux51test.v
module mux51test();
//Performance Cost: 9 + 1?
reg [4:0] inA, inB;
reg inS;
wire [4:0] outO;

mux51 DUT(inA, inB, inS, outO);
initial
begin
	$dumpfile("gtk/mux51-gtkwave.vcd");
	$dumpvars(0, DUT);

	$display("Test Start");
	inA <= 5'b01110;
	inB <= 5'b10001;
	inS <= 0;
	#10
	$display("inA = %b\ninB = %b\ninS = %b", inA, inB, inS);
	$display("outO is = %b\n", outO);

	inA <= 5'b01110;
	inB <= 5'b10001;
	inS <= 1;
	#10
	$display("inA = %b\ninB = %b\ninS = %b", inA, inB, inS);
	$display("outO is = %b\n", outO);

	inA <= 5'b10001;
	inB <= 5'b01110;
	inS <= 0;
	#10
	$display("inA = %b\ninB = %b\ninS = %b", inA, inB, inS);
	$display("outO is = %b\n", outO);

	inA <= 5'b10001;
	inB <= 5'b01110;
	inS <= 1;
	#10
	$display("inA = %b\ninB = %b\ninS = %b", inA, inB, inS);
	$display("outO is = %b\n", outO);
end
endmodule

gtk/mux51-gtkwave.vcd
$date
	Sat Feb 23 22:27:15 2019
$end
$version
	Icarus Verilog
$end
$timescale
	1s
$end
$scope module mux51test $end
$scope module DUT $end
$var wire 5 ! inA [4:0] $end
$var wire 5 " inB [4:0] $end
$var wire 1 # inS $end
$var wire 5 $ outO [4:0] $end
$scope module mux0 $end
$var wire 1 % Snot $end
$var wire 1 & T1 $end
$var wire 1 ' T2 $end
$var wire 1 ( inA $end
$var wire 1 ) inB $end
$var wire 1 # inS $end
$var wire 1 * outO $end
$upscope $end
$scope module mux1 $end
$var wire 1 + Snot $end
$var wire 1 , T1 $end
$var wire 1 - T2 $end
$var wire 1 . inA $end
$var wire 1 / inB $end
$var wire 1 # inS $end
$var wire 1 0 outO $end
$upscope $end
$scope module mux2 $end
$var wire 1 1 Snot $end
$var wire 1 2 T1 $end
$var wire 1 3 T2 $end
$var wire 1 4 inA $end
$var wire 1 5 inB $end
$var wire 1 # inS $end
$var wire 1 6 outO $end
$upscope $end
$scope module mux3 $end
$var wire 1 7 Snot $end
$var wire 1 8 T1 $end
$var wire 1 9 T2 $end
$var wire 1 : inA $end
$var wire 1 ; inB $end
$var wire 1 # inS $end
$var wire 1 < outO $end
$upscope $end
$scope module mux4 $end
$var wire 1 = Snot $end
$var wire 1 > T1 $end
$var wire 1 ? T2 $end
$var wire 1 @ inA $end
$var wire 1 A inB $end
$var wire 1 # inS $end
$var wire 1 B outO $end
$upscope $end
$upscope $end
$upscope $end
$enddefinitions $end
#0
$dumpvars
xB
1A
0@
x?
x>
x=
x<
0;
1:
x9
x8
x7
x6
05
14
x3
x2
x1
x0
0/
1.
x-
x,
x+
x*
1)
0(
x'
x&
x%
bx $
0#
b10001 "
b1110 !
$end
#1
1%
1+
11
17
1=
#4
0&
0>
0'
0-
03
09
0?
#5
1,
12
18
#8
0*
b0xxx0 $
0B
#9
10
16
b1110 $
1<
#10
1#
#11
0%
0+
01
07
0=
#14
1'
1?
#15
0,
02
08
#18
1*
b11111 $
1B
#19
00
06
b10001 $
0<
#20
0)
1/
15
1;
0A
1(
0.
04
0:
1@
0#
b1110 "
b10001 !
#21
1%
1+
11
17
1=
#24
0'
0?
#25
1&
1>
#30
1#
#31
0%
0+
01
07
0=
#34
1-
13
19
#35
0&
0>
#38
10
16
b11111 $
1<
#39
0*
b1110 $
0B
